{"type": "Feature", "id": 12523920, "properties": {"woe:id": 12523920, "woe:parent_id": 483301, "woe:name": "Monte Carlo Heliport", "woe:placetype": 14, "woe:placetype_name": "Airport", "woe:lang": "ENG", "iso:country": "MC", "meta:provider": ["geoplanet:7.3.1", "geoplanet:7.3.2", "geoplanet:7.4.0", "geoplanet:7.4.1", "geoplanet:7.5.1", "geoplanet:7.5.2", "geoplanet:7.6.0", "geoplanet:7.8.1", "geoplanet:7.9.0", "geoplanet:7.10.0", "geoplanet:8.0.0", "woeplanet:8.0.0"], "meta:indexed": "2020-08-20T20:58:45.104740", "woe:alias_ENG_V": ["MCM Airport", "MCM", "Mte Carlo Heliport"], "meta:updated": "2020-08-22T02:58:57.105931", "woe:hierarchy": {"continent": 24865675, "country": 23424892, "town": 0, "planet": 1, "county": 0, "suburb": 0, "state": 24549796, "region": 0, "localadmin": 0}, "woe:timezone_id": 28350908, "woe:hash": "spv2bb6hv7hc", "woe:centroid": [7.41875, 43.727791], "geom:latitude": 43.727791, "geom:longitude": 7.41875, "geom:hash": "spv2bb6hv7hc", "woe:latitude": 43.727791, "geom:centroid": [7.41875, 43.727791], "woe:longitude": 7.41875, "woe:repo": "woeplanet-airport-mc"}, "geometry": {"coordinates": [7.41875, 43.727791], "type": "Point"}}